pypoller/__init__.py
pypoller/messaging/CombinedMessage.py
pypoller/messaging/CombinedNotifier.py
pypoller/messaging/ConsoleNotifier.py
pypoller/messaging/Message.py
pypoller/messaging/NotificationException.py
pypoller/messaging/Notifier.py
pypoller/messaging/RocketChatNotifier.py
pypoller/messaging/TryNextOnFailNotifier.py
pypoller/messaging/TwilioSMSNotifier.py
pypoller/messaging/__init__.py
pypoller/messaging/contact/Contact.py
pypoller/messaging/contact/EmailContact.py
pypoller/messaging/contact/PhoneContact.py
pypoller/messaging/contact/RCContact.py
pypoller/messaging/contact/__init__.py
pypoller/poller/Poller.py
pypoller/poller/__init__.py
pypoller/resource/MulitpleResourceChecker.py
pypoller/resource/ParksCanadaChecker.py
pypoller/resource/ResourceChecker.py
pypoller/resource/USVisaResourceChecker.py
pypoller/resource/__init__.py
pypoller/resource/request/DateRangeRequest.py
pypoller/resource/request/Request.py
pypoller/resource/request/__init__.py
pypoller/resource/response/CombinedResponse.py
pypoller/resource/response/Response.py
pypoller/resource/response/__init__.py
pypoller/util/__init__.py
pypoller/util/decorators.py
pypoller-0.1.6.dist-info/LICENSE
pypoller-0.1.6.dist-info/METADATA
pypoller-0.1.6.dist-info/WHEEL
pypoller-0.1.6.dist-info/top_level.txt
pypoller-0.1.6.dist-info/RECORD
