Metadata-Version: 2.1
Name: pypoller
Version: 0.1.6
Summary: Lightweight polling and notification framework
Author-email: Mohit Chauhan <mhchauhan3@gmail.com>
Project-URL: Homepage, https://www.mohitc.com/pypoller
Project-URL: Source, https://github.com/mchauhan3/pypoller
Classifier: Development Status :: 4 - Beta
Classifier: Intended Audience :: Developers
Classifier: Topic :: Software Development :: Libraries
Classifier: License :: OSI Approved :: MIT License
Requires-Python: >=3.9
License-File: LICENSE
Requires-Dist: requests
Requires-Dist: playwright
Requires-Dist: twilio
Requires-Dist: typing-extensions
Requires-Dist: python-dotenv
Requires-Dist: rocketchat-API
